metorial/__init__.py
metorial/_base.py
metorial/_client.py
metorial/_client_core.py
metorial/_config.py
metorial/_executor.py
metorial/_protocols.py
metorial/_raw_response.py
metorial/_safe_cleanup.py
metorial/_sdk.py
metorial/_sdk_builder.py
metorial/_session.py
metorial/_streaming.py
metorial/_sync_client.py
metorial/_tool_adapters.py
metorial/_tool_manager.py
metorial/_typed_endpoints.py
metorial/_types.py
metorial/_version.py
metorial/exceptions.py
metorial/py.typed
metorial/utils.py
metorial/_endpoint/__init__.py
metorial/_endpoint/base_endpoint.py
metorial/_endpoint/endpoint_manager.py
metorial/_endpoint/request.py
metorial/_generated/__init__.py
metorial/_generated/dashboard/__init__.py
metorial/_generated/dashboard/endpoints/__init__.py
metorial/_generated/dashboard/endpoints/api_keys.py
metorial/_generated/dashboard/endpoints/callbacks.py
metorial/_generated/dashboard/endpoints/callbacks_destinations.py
metorial/_generated/dashboard/endpoints/callbacks_events.py
metorial/_generated/dashboard/endpoints/callbacks_notifications.py
metorial/_generated/dashboard/endpoints/custom_servers.py
metorial/_generated/dashboard/endpoints/custom_servers_code.py
metorial/_generated/dashboard/endpoints/custom_servers_deployments.py
metorial/_generated/dashboard/endpoints/custom_servers_events.py
metorial/_generated/dashboard/endpoints/custom_servers_listing.py
metorial/_generated/dashboard/endpoints/custom_servers_managed_server_templates.py
metorial/_generated/dashboard/endpoints/custom_servers_remote_servers.py
metorial/_generated/dashboard/endpoints/custom_servers_versions.py
metorial/_generated/dashboard/endpoints/dashboard.py
metorial/_generated/dashboard/endpoints/dashboard_instance_callbacks.py
metorial/_generated/dashboard/endpoints/dashboard_instance_callbacks_destinations.py
metorial/_generated/dashboard/endpoints/dashboard_instance_callbacks_events.py
metorial/_generated/dashboard/endpoints/dashboard_instance_callbacks_notifications.py
metorial-2.0.0.dist-info/METADATA
metorial-2.0.0.dist-info/WHEEL
metorial-2.0.0.dist-info/licenses/LICENSE
metorial-2.0.0.dist-info/RECORD
