Metadata-Version: 2.4
Name: metorial
Version: 2.0.0
Summary: Python SDK for Metorial - The open source integration platform for agentic AI
Project-URL: Homepage, https://metorial.com
Project-URL: Documentation, https://metorial.com/docs
Project-URL: Repository, https://github.com/metorial/metorial-python
Author-email: Metorial Team <support@metorial.com>
License: MIT
License-File: LICENSE
Keywords: ai,anthropic,llm,mcp,metorial,openai
Classifier: Development Status :: 4 - Beta
Classifier: Intended Audience :: Developers
Classifier: License :: OSI Approved :: MIT License
Classifier: Programming Language :: Python :: 3
Classifier: Programming Language :: Python :: 3.10
Classifier: Programming Language :: Python :: 3.11
Classifier: Programming Language :: Python :: 3.12
Classifier: Typing :: Typed
Requires-Python: >=3.10
Requires-Dist: aiohttp-sse-client>=0.2.1
Requires-Dist: aiohttp>=3.8.0
Requires-Dist: anthropic>=0.69.0
Requires-Dist: google-generativeai>=0.3.0
Requires-Dist: httpx>=0.25.0
Requires-Dist: mcp>=1.0.0
Requires-Dist: mistralai>=1.0.0
Requires-Dist: openai>=1.0.0
Requires-Dist: requests>=2.25.0
Requires-Dist: truststore>=0.8.0
Requires-Dist: typing-extensions>=4.0.0
Provides-Extra: dev
Requires-Dist: mypy>=1.0.0; extra == 'dev'
Requires-Dist: pre-commit>=3.5.0; extra == 'dev'
Requires-Dist: pytest-asyncio>=0.20.0; extra == 'dev'
Requires-Dist: pytest>=7.0.0; extra == 'dev'
Requires-Dist: ruff>=0.4.0; extra == 'dev'
Requires-Dist: types-requests>=2.32.0; extra == 'dev'
